mountaineer_exceptions/__init__.py
mountaineer_exceptions/cli.py
mountaineer_exceptions/plugin.py
mountaineer_exceptions/py.typed
mountaineer_exceptions/__tests__/__init__.py
mountaineer_exceptions/__tests__/controllers/__init__.py
mountaineer_exceptions/__tests__/controllers/test_exception_controller.py
mountaineer_exceptions/__tests__/controllers/test_traceback.py
mountaineer_exceptions/__tests__/fixtures/__init__.py
mountaineer_exceptions/__tests__/fixtures/example_view/package-lock.json
mountaineer_exceptions/__tests__/fixtures/example_view/package.json
mountaineer_exceptions/__tests__/fixtures/example_view/broken/page.tsx
mountaineer_exceptions/controllers/__init__.py
mountaineer_exceptions/controllers/exception_controller.py
mountaineer_exceptions/controllers/traceback.py
mountaineer_exceptions/views/__init__.py
mountaineer_exceptions/views/biome.json
mountaineer_exceptions/views/package-lock.json
mountaineer_exceptions/views/package.json
mountaineer_exceptions/views/postcss.config.mjs
mountaineer_exceptions/views/tsconfig.json
mountaineer_exceptions/views/_ssr/exception_controller.js
mountaineer_exceptions/views/_ssr/layout_1d9fb5183fb8e20953114b6062f2f180.js
mountaineer_exceptions/views/_static/client-BAxOOlQe.js
mountaineer_exceptions/views/_static/core_main.css
mountaineer_exceptions/views/_static/exception_controller.js
mountaineer_exceptions/views/_static/exception_controller.map.js
mountaineer_exceptions/views/_static/layout_1d9fb5183fb8e20953114b6062f2f180.js
mountaineer_exceptions/views/_static/layout_1d9fb5183fb8e20953114b6062f2f180.map.js
mountaineer_exceptions/views/core/layout.tsx
mountaineer_exceptions/views/core/main.css
mountaineer_exceptions/views/core/exception/page.tsx
mountaineer_exceptions-0.1.1.dist-info/METADATA
mountaineer_exceptions-0.1.1.dist-info/WHEEL
mountaineer_exceptions-0.1.1.dist-info/entry_points.txt
mountaineer_exceptions-0.1.1.dist-info/RECORD
