Metadata-Version: 2.4
Name: mountaineer-exceptions
Version: 0.1.1
Summary: A small plugin for mountaineer that shows beautiful tracebacks in the browser.
Requires-Python: >=3.10
Requires-Dist: pygments>=2.19.1
